README.md
setup.py
scrapy_autounit/__init__.py
scrapy_autounit/cassette.py
scrapy_autounit/cli.py
scrapy_autounit/middleware.py
scrapy_autounit/parser.py
scrapy_autounit/player.py
scrapy_autounit/recorder.py
scrapy_autounit/utils.py
scrapy_autounit.egg-info/PKG-INFO
scrapy_autounit.egg-info/SOURCES.txt
scrapy_autounit.egg-info/dependency_links.txt
scrapy_autounit.egg-info/entry_points.txt
scrapy_autounit.egg-info/requires.txt
scrapy_autounit.egg-info/top_level.txt
tests/__init__.py
tests/test_middleware.py
tests/test_record.py