Metadata-Version: 2.1
Name: scrapy-autounit
Version: 0.0.28
Summary: Automatic unit test generation for Scrapy.
Home-page: https://github.com/scrapinghub/scrapy-autounit
Author: 
Author-email: 
License: UNKNOWN
Platform: UNKNOWN
Classifier: Programming Language :: Python :: 2.7
Classifier: Programming Language :: Python :: 3
Classifier: License :: OSI Approved :: BSD License
Classifier: Operating System :: OS Independent
